bean/__init__.py
bean/annotate/filter_alleles.py
bean/annotate/ldlr_exons.fa
bean/annotate/translate_allele.py
bean/annotate/utils.py
bean/annotate/_supporting_fn.py
bean/annotate/__init__.py
bean/cli/count.py
bean/cli/count_samples.py
bean/cli/create_screen.py
bean/cli/execute.py
bean/cli/filter.py
bean/cli/get_splice_sites.py
bean/cli/profile.py
bean/cli/qc.py
bean/cli/run.py
bean/cli/__init__.py
bean/framework/allele_counts.py
bean/framework/AminoAcidEdit.py
bean/framework/Edit.py
bean/framework/parser.py
bean/framework/read_from_csvs.py
bean/framework/ReporterScreen.py
bean/framework/__init__.py
bean/framework/__pycache__/ReporterScreen_.py
bean/mapping/CRISPResso2Align.c
bean/mapping/CRISPResso2Align.cpython-38-x86_64-linux-gnu.so
bean/mapping/CRISPResso2Align.pyx
bean/mapping/GuideEditCounter.py
bean/mapping/utils.py
bean/mapping/_supporting_fn.py
bean/mapping/__init__.py
bean/model/model.py
bean/model/parser.py
bean/model/readwrite.py
bean/model/run.py
bean/model/survival_model.py
bean/model/utils.py
bean/model/__init__.py
bean/notebooks/profile_editing_preference.ipynb
bean/notebooks/sample_quality_report.ipynb
bean/plotting/allele_stats.py
bean/plotting/editing_patterns.py
bean/plotting/parser.py
bean/plotting/utils.py
bean/plotting/__init__.py
bean/preprocessing/data_class.py
bean/preprocessing/get_alpha0.py
bean/preprocessing/get_pi_alpha0.py
bean/preprocessing/utils.py
bean/preprocessing/__init__.py
bean/qc/guide_qc.py
bean/qc/parser.py
bean/qc/sample_qc.py
bean/qc/utils.py
bean/qc/__init__.py
bean/utils/arithmetric.py
bean/utils/plot.py
bean/utils/__init__.py
bin/bean
crispr_bean-1.2.8.data/scripts/bean
crispr_bean-1.2.8.dist-info/LICENSE
crispr_bean-1.2.8.dist-info/METADATA
crispr_bean-1.2.8.dist-info/RECORD
crispr_bean-1.2.8.dist-info/top_level.txt
crispr_bean-1.2.8.dist-info/WHEEL
docs/conf.py
docs/count.rst
docs/count_samples.rst
docs/create_screen.rst
docs/editing_pattern_analysis.ipynb
docs/exon_fa_format.md
docs/filter.rst
docs/index.rst
docs/input.rst
docs/make.bat
docs/Makefile
docs/profile.rst
docs/qc.rst
docs/qc_report_LDLvar.html
