Metadata-Version: 2.1
Name: crispr-bean
Version: 1.2.8
Summary: Base Editor screen analysis with guide Activity Normalization
Home-page: https://github.com/pinellolab/crispr-bean
Author: Jayoung Ryu
Author-email: jayoung_ryu@g.harvard.edu
License: UNKNOWN
Platform: UNKNOWN
Classifier: Programming Language :: Python :: 3
Classifier: Operating System :: OS Independent
Requires-Python: >=3.8.0
Requires-Dist: numpy
Requires-Dist: pandas
Requires-Dist: scipy
Requires-Dist: perturb-tools (>=0.3.4)
Requires-Dist: matplotlib (<3.9)
Requires-Dist: seaborn (>=0.13.0)
Requires-Dist: tqdm
Requires-Dist: bio
Requires-Dist: liftover
Requires-Dist: openpyxl (>=3.0.10)
Requires-Dist: papermill (>=2.4.0)
Requires-Dist: pyBigWig (>=0.3.18)
Requires-Dist: pyro-ppl (>=1.8.5)
Requires-Dist: scikit-learn
Requires-Dist: statsmodels (>=0.12.1)
Requires-Dist: ipykernel
Requires-Dist: pytest-order
Requires-Dist: nbconvert
Requires-Dist: logomaker
Requires-Dist: ipywidgets
